imgcompressionkit/__init__.py
imgcompressionkit/algorithms.py
imgcompressionkit/tools.py
imgcompressionkit-0.3.dist-info/METADATA
imgcompressionkit-0.3.dist-info/WHEEL
imgcompressionkit-0.3.dist-info/top_level.txt
imgcompressionkit-0.3.dist-info/RECORD
